setup.py
app/__init__.py
app/__main__.py
bin/windMailer.sh
windMailer.egg-info/PKG-INFO
windMailer.egg-info/SOURCES.txt
windMailer.egg-info/dependency_links.txt
windMailer.egg-info/entry_points.txt
windMailer.egg-info/requires.txt
windMailer.egg-info/top_level.txt