Metadata-Version: 1.0
Name: windMailer
Version: 0.2.5
Summary: Useful towel-related stuff. 
Home-page: http://pypi.python.org/pypi/windMailer_v025/
Author: dukeman
Author-email: gabeduke@gmail.com
License: UNKNOWN
Platform: UNKNOWN
